{"openapi":"3.1.0","info":{"title":"ProcuraHub","version":"0.1.0"},"paths":{"/api/auth/token":{"post":{"tags":["auth"],"summary":"Login For Access Token","operationId":"login_for_access_token_api_auth_token_post","requestBody":{"content":{"application/x-www-form-urlencoded":{"schema":{"$ref":"#/components/schemas/Body_login_for_access_token_api_auth_token_post"}}},"required":true},"responses":{"200":{"description":"Successful Response","content":{"application/json":{"schema":{"$ref":"#/components/schemas/Token"}}}},"422":{"description":"Validation Error","content":{"application/json":{"schema":{"$ref":"#/components/schemas/HTTPValidationError"}}}}}}},"/api/auth/users":{"post":{"tags":["auth"],"summary":"Create User Account","operationId":"create_user_account_api_auth_users_post","requestBody":{"content":{"application/json":{"schema":{"$ref":"#/components/schemas/UserCreate"}}},"required":true},"responses":{"201":{"description":"Successful Response","content":{"application/json":{"schema":{"$ref":"#/components/schemas/UserRead"}}}},"422":{"description":"Validation Error","content":{"application/json":{"schema":{"$ref":"#/components/schemas/HTTPValidationError"}}}}},"security":[{"OAuth2PasswordBearer":[]}]}},"/api/auth/me":{"get":{"tags":["auth"],"summary":"Read Current User","operationId":"read_current_user_api_auth_me_get","responses":{"200":{"description":"Successful Response","content":{"application/json":{"schema":{"$ref":"#/components/schemas/UserRead"}}}}},"security":[{"OAuth2PasswordBearer":[]}]}},"/api/suppliers/register":{"post":{"tags":["suppliers"],"summary":"Register Supplier","description":"Register a supplier account along with supporting documents.","operationId":"register_supplier_api_suppliers_register_post","requestBody":{"content":{"multipart/form-data":{"schema":{"$ref":"#/components/schemas/Body_register_supplier_api_suppliers_register_post"}}},"required":true},"responses":{"201":{"description":"Successful Response","content":{"application/json":{"schema":{"$ref":"#/components/schemas/SupplierRegistrationResponse"}}}},"422":{"description":"Validation Error","content":{"application/json":{"schema":{"$ref":"#/components/schemas/HTTPValidationError"}}}}}}},"/api/suppliers/me/profile":{"get":{"tags":["suppliers"],"summary":"Get My Profile","operationId":"get_my_profile_api_suppliers_me_profile_get","responses":{"200":{"description":"Successful Response","content":{"application/json":{"schema":{"$ref":"#/components/schemas/SupplierProfileRead"}}}}},"security":[{"OAuth2PasswordBearer":[]}]}},"/api/suppliers/me/invitations":{"get":{"tags":["suppliers"],"summary":"Get My Invitations","operationId":"get_my_invitations_api_suppliers_me_invitations_get","responses":{"200":{"description":"Successful Response","content":{"application/json":{"schema":{}}}}},"security":[{"OAuth2PasswordBearer":[]}]}},"/api/suppliers/me/rfqs/active":{"get":{"tags":["suppliers"],"summary":"List Active Rfqs For Supplier","operationId":"list_active_rfqs_for_supplier_api_suppliers_me_rfqs_active_get","responses":{"200":{"description":"Successful Response","content":{"application/json":{"schema":{}}}}},"security":[{"OAuth2PasswordBearer":[]}]}},"/api/rfqs/":{"get":{"tags":["rfqs"],"summary":"List Rfqs","operationId":"list_rfqs_api_rfqs__get","responses":{"200":{"description":"Successful Response","content":{"application/json":{"schema":{"items":{"$ref":"#/components/schemas/RFQRead"},"type":"array","title":"Response List Rfqs Api Rfqs  Get"}}}}},"security":[{"OAuth2PasswordBearer":[]}]},"post":{"tags":["rfqs"],"summary":"Create Rfq","operationId":"create_rfq_api_rfqs__post","requestBody":{"content":{"application/json":{"schema":{"$ref":"#/components/schemas/RFQCreate"}}},"required":true},"responses":{"201":{"description":"Successful Response","content":{"application/json":{"schema":{"$ref":"#/components/schemas/RFQRead"}}}},"422":{"description":"Validation Error","content":{"application/json":{"schema":{"$ref":"#/components/schemas/HTTPValidationError"}}}}},"security":[{"OAuth2PasswordBearer":[]}]}},"/api/rfqs/{rfq_id}":{"get":{"tags":["rfqs"],"summary":"Read Rfq","operationId":"read_rfq_api_rfqs__rfq_id__get","security":[{"OAuth2PasswordBearer":[]}],"parameters":[{"name":"rfq_id","in":"path","required":true,"schema":{"type":"integer","title":"Rfq Id"}}],"responses":{"200":{"description":"Successful Response","content":{"application/json":{"schema":{"$ref":"#/components/schemas/RFQWithQuotations"}}}},"422":{"description":"Validation Error","content":{"application/json":{"schema":{"$ref":"#/components/schemas/HTTPValidationError"}}}}}},"put":{"tags":["rfqs"],"summary":"Update Rfq","operationId":"update_rfq_api_rfqs__rfq_id__put","security":[{"OAuth2PasswordBearer":[]}],"parameters":[{"name":"rfq_id","in":"path","required":true,"schema":{"type":"integer","title":"Rfq Id"}}],"requestBody":{"required":true,"content":{"application/json":{"schema":{"$ref":"#/components/schemas/RFQUpdate"}}}},"responses":{"200":{"description":"Successful Response","content":{"application/json":{"schema":{"$ref":"#/components/schemas/RFQRead"}}}},"422":{"description":"Validation Error","content":{"application/json":{"schema":{"$ref":"#/components/schemas/HTTPValidationError"}}}}}}},"/api/rfqs/{rfq_id}/quotations":{"post":{"tags":["rfqs"],"summary":"Submit Quotation","operationId":"submit_quotation_api_rfqs__rfq_id__quotations_post","security":[{"OAuth2PasswordBearer":[]}],"parameters":[{"name":"rfq_id","in":"path","required":true,"schema":{"type":"integer","title":"Rfq Id"}}],"requestBody":{"required":true,"content":{"multipart/form-data":{"schema":{"$ref":"#/components/schemas/Body_submit_quotation_api_rfqs__rfq_id__quotations_post"}}}},"responses":{"201":{"description":"Successful Response","content":{"application/json":{"schema":{}}}},"422":{"description":"Validation Error","content":{"application/json":{"schema":{"$ref":"#/components/schemas/HTTPValidationError"}}}}}}},"/api/rfqs/{rfq_id}/quotations/{quotation_id}/approve":{"post":{"tags":["rfqs"],"summary":"Approve Quotation","operationId":"approve_quotation_api_rfqs__rfq_id__quotations__quotation_id__approve_post","security":[{"OAuth2PasswordBearer":[]}],"parameters":[{"name":"rfq_id","in":"path","required":true,"schema":{"type":"integer","title":"Rfq Id"}},{"name":"quotation_id","in":"path","required":true,"schema":{"type":"integer","title":"Quotation Id"}}],"responses":{"200":{"description":"Successful Response","content":{"application/json":{"schema":{}}}},"422":{"description":"Validation Error","content":{"application/json":{"schema":{"$ref":"#/components/schemas/HTTPValidationError"}}}}}}},"/api/admin/users":{"get":{"tags":["admin"],"summary":"List Users","description":"List all users in the system.","operationId":"list_users_api_admin_users_get","responses":{"200":{"description":"Successful Response","content":{"application/json":{"schema":{"items":{"$ref":"#/components/schemas/UserRead"},"type":"array","title":"Response List Users Api Admin Users Get"}}}}},"security":[{"OAuth2PasswordBearer":[]}]},"post":{"tags":["admin"],"summary":"Create New User","description":"Create a new user (SuperAdmin only).","operationId":"create_new_user_api_admin_users_post","requestBody":{"content":{"application/json":{"schema":{"$ref":"#/components/schemas/UserCreate"}}},"required":true},"responses":{"201":{"description":"Successful Response","content":{"application/json":{"schema":{"$ref":"#/components/schemas/UserRead"}}}},"422":{"description":"Validation Error","content":{"application/json":{"schema":{"$ref":"#/components/schemas/HTTPValidationError"}}}}},"security":[{"OAuth2PasswordBearer":[]}]}},"/api/admin/users/{user_id}":{"delete":{"tags":["admin"],"summary":"Delete User","description":"Delete a user (SuperAdmin only, cannot delete self).","operationId":"delete_user_api_admin_users__user_id__delete","security":[{"OAuth2PasswordBearer":[]}],"parameters":[{"name":"user_id","in":"path","required":true,"schema":{"type":"integer","title":"User Id"}}],"responses":{"204":{"description":"Successful Response"},"422":{"description":"Validation Error","content":{"application/json":{"schema":{"$ref":"#/components/schemas/HTTPValidationError"}}}}}}},"/api/admin/suppliers":{"get":{"tags":["admin"],"summary":"List Suppliers","description":"List all registered suppliers (SuperAdmin and Procurement).","operationId":"list_suppliers_api_admin_suppliers_get","security":[{"OAuth2PasswordBearer":[]}],"responses":{"200":{"description":"Successful Response","content":{"application/json":{"schema":{"type":"array","items":{"type":"object","additionalProperties":true},"title":"Response List Suppliers Api Admin Suppliers Get"}}}}}},"post":{"tags":["admin"],"summary":"Create Supplier By Procurement","description":"Create a supplier account (SuperAdmin and Procurement).","operationId":"create_supplier_by_procurement_api_admin_suppliers_post","security":[{"OAuth2PasswordBearer":[]}],"parameters":[{"name":"company_name","in":"query","required":true,"schema":{"type":"string","title":"Company Name"}},{"name":"contact_email","in":"query","required":true,"schema":{"type":"string","title":"Contact Email"}},{"name":"full_name","in":"query","required":true,"schema":{"type":"string","title":"Full Name"}},{"name":"password","in":"query","required":true,"schema":{"type":"string","title":"Password"}},{"name":"contact_phone","in":"query","required":false,"schema":{"anyOf":[{"type":"string"},{"type":"null"}],"title":"Contact Phone"}},{"name":"address","in":"query","required":false,"schema":{"anyOf":[{"type":"string"},{"type":"null"}],"title":"Address"}},{"name":"preferred_currency","in":"query","required":false,"schema":{"anyOf":[{"type":"string"},{"type":"null"}],"default":"USD","title":"Preferred Currency"}}],"responses":{"201":{"description":"Successful Response","content":{"application/json":{"schema":{"type":"object","additionalProperties":true,"title":"Response Create Supplier By Procurement Api Admin Suppliers Post"}}}},"422":{"description":"Validation Error","content":{"application/json":{"schema":{"$ref":"#/components/schemas/HTTPValidationError"}}}}}}},"/api/admin/categories":{"get":{"tags":["admin"],"summary":"List Categories","description":"List all procurement categories.","operationId":"list_categories_api_admin_categories_get","responses":{"200":{"description":"Successful Response","content":{"application/json":{"schema":{"items":{"$ref":"#/components/schemas/CategoryRead"},"type":"array","title":"Response List Categories Api Admin Categories Get"}}}}},"security":[{"OAuth2PasswordBearer":[]}]},"post":{"tags":["admin"],"summary":"Create Category","description":"Create a new procurement category.","operationId":"create_category_api_admin_categories_post","requestBody":{"content":{"application/json":{"schema":{"$ref":"#/components/schemas/CategoryCreate"}}},"required":true},"responses":{"201":{"description":"Successful Response","content":{"application/json":{"schema":{"$ref":"#/components/schemas/CategoryRead"}}}},"422":{"description":"Validation Error","content":{"application/json":{"schema":{"$ref":"#/components/schemas/HTTPValidationError"}}}}},"security":[{"OAuth2PasswordBearer":[]}]}},"/api/admin/categories/{category_id}":{"put":{"tags":["admin"],"summary":"Update Category","description":"Update a procurement category.","operationId":"update_category_api_admin_categories__category_id__put","security":[{"OAuth2PasswordBearer":[]}],"parameters":[{"name":"category_id","in":"path","required":true,"schema":{"type":"integer","title":"Category Id"}}],"requestBody":{"required":true,"content":{"application/json":{"schema":{"$ref":"#/components/schemas/CategoryUpdate"}}}},"responses":{"200":{"description":"Successful Response","content":{"application/json":{"schema":{"$ref":"#/components/schemas/CategoryRead"}}}},"422":{"description":"Validation Error","content":{"application/json":{"schema":{"$ref":"#/components/schemas/HTTPValidationError"}}}}}},"delete":{"tags":["admin"],"summary":"Delete Category","description":"Delete a procurement category.","operationId":"delete_category_api_admin_categories__category_id__delete","security":[{"OAuth2PasswordBearer":[]}],"parameters":[{"name":"category_id","in":"path","required":true,"schema":{"type":"integer","title":"Category Id"}}],"responses":{"204":{"description":"Successful Response"},"422":{"description":"Validation Error","content":{"application/json":{"schema":{"$ref":"#/components/schemas/HTTPValidationError"}}}}}}},"/health":{"get":{"summary":"Healthcheck","operationId":"healthcheck_health_get","responses":{"200":{"description":"Successful Response","content":{"application/json":{"schema":{"additionalProperties":{"type":"string"},"type":"object","title":"Response Healthcheck Health Get"}}}}}}}},"components":{"schemas":{"Body_login_for_access_token_api_auth_token_post":{"properties":{"grant_type":{"anyOf":[{"type":"string","pattern":"^password$"},{"type":"null"}],"title":"Grant Type"},"username":{"type":"string","title":"Username"},"password":{"type":"string","format":"password","title":"Password"},"scope":{"type":"string","title":"Scope","default":""},"client_id":{"anyOf":[{"type":"string"},{"type":"null"}],"title":"Client Id"},"client_secret":{"anyOf":[{"type":"string"},{"type":"null"}],"format":"password","title":"Client Secret"}},"type":"object","required":["username","password"],"title":"Body_login_for_access_token_api_auth_token_post"},"Body_register_supplier_api_suppliers_register_post":{"properties":{"company_name":{"type":"string","title":"Company Name"},"full_name":{"type":"string","title":"Full Name"},"email":{"type":"string","title":"Email"},"password":{"type":"string","title":"Password"},"contact_phone":{"anyOf":[{"type":"string"},{"type":"null"}],"title":"Contact Phone"},"address":{"anyOf":[{"type":"string"},{"type":"null"}],"title":"Address"},"preferred_currency":{"anyOf":[{"type":"string"},{"type":"null"}],"title":"Preferred Currency","default":"USD"},"categories":{"anyOf":[{"type":"string"},{"type":"null"}],"title":"Categories"},"incorporation_file":{"anyOf":[{"type":"string","format":"binary"},{"type":"null"}],"title":"Incorporation File"},"tax_clearance_file":{"anyOf":[{"type":"string","format":"binary"},{"type":"null"}],"title":"Tax Clearance File"},"company_profile_file":{"anyOf":[{"type":"string","format":"binary"},{"type":"null"}],"title":"Company Profile File"}},"type":"object","required":["company_name","full_name","email","password"],"title":"Body_register_supplier_api_suppliers_register_post"},"Body_submit_quotation_api_rfqs__rfq_id__quotations_post":{"properties":{"amount":{"anyOf":[{"type":"number"},{"type":"string","pattern":"^(?!^[-+.]*$)[+-]?0*\\d*\\.?\\d*$"}],"title":"Amount"},"currency":{"type":"string","title":"Currency","default":"USD"},"notes":{"anyOf":[{"type":"string"},{"type":"null"}],"title":"Notes"},"attachment":{"anyOf":[{"type":"string","format":"binary"},{"type":"null"}],"title":"Attachment"}},"type":"object","required":["amount"],"title":"Body_submit_quotation_api_rfqs__rfq_id__quotations_post"},"CategoryCreate":{"properties":{"name":{"type":"string","title":"Name"},"description":{"anyOf":[{"type":"string"},{"type":"null"}],"title":"Description"}},"type":"object","required":["name"],"title":"CategoryCreate"},"CategoryRead":{"properties":{"name":{"type":"string","title":"Name"},"description":{"anyOf":[{"type":"string"},{"type":"null"}],"title":"Description"},"id":{"type":"integer","title":"Id"},"created_at":{"anyOf":[{"type":"string","format":"date-time"},{"type":"null"}],"title":"Created At"},"updated_at":{"anyOf":[{"type":"string","format":"date-time"},{"type":"null"}],"title":"Updated At"}},"type":"object","required":["name","id"],"title":"CategoryRead"},"CategoryUpdate":{"properties":{"name":{"anyOf":[{"type":"string"},{"type":"null"}],"title":"Name"},"description":{"anyOf":[{"type":"string"},{"type":"null"}],"title":"Description"}},"type":"object","title":"CategoryUpdate"},"HTTPValidationError":{"properties":{"detail":{"items":{"$ref":"#/components/schemas/ValidationError"},"type":"array","title":"Detail"}},"type":"object","title":"HTTPValidationError"},"QuotationRead-Input":{"properties":{"id":{"type":"integer","title":"Id"},"rfq_id":{"type":"integer","title":"Rfq Id"},"supplier_id":{"type":"integer","title":"Supplier Id"},"amount":{"anyOf":[{"type":"number"},{"type":"string","pattern":"^(?!^[-+.]*$)[+-]?0*\\d*\\.?\\d*$"}],"title":"Amount"},"currency":{"type":"string","title":"Currency"},"notes":{"anyOf":[{"type":"string"},{"type":"null"}],"title":"Notes"},"status":{"type":"string","title":"Status"},"submitted_at":{"type":"string","format":"date-time","title":"Submitted At"},"approved_at":{"anyOf":[{"type":"string","format":"date-time"},{"type":"null"}],"title":"Approved At"}},"type":"object","required":["id","rfq_id","supplier_id","amount","currency","notes","status","submitted_at","approved_at"],"title":"QuotationRead"},"QuotationRead-Output":{"properties":{"id":{"type":"integer","title":"Id"},"rfq_id":{"type":"integer","title":"Rfq Id"},"supplier_id":{"type":"integer","title":"Supplier Id"},"amount":{"type":"string","pattern":"^(?!^[-+.]*$)[+-]?0*\\d*\\.?\\d*$","title":"Amount"},"currency":{"type":"string","title":"Currency"},"notes":{"anyOf":[{"type":"string"},{"type":"null"}],"title":"Notes"},"status":{"type":"string","title":"Status"},"submitted_at":{"type":"string","format":"date-time","title":"Submitted At"},"approved_at":{"anyOf":[{"type":"string","format":"date-time"},{"type":"null"}],"title":"Approved At"}},"type":"object","required":["id","rfq_id","supplier_id","amount","currency","notes","status","submitted_at","approved_at"],"title":"QuotationRead"},"RFQCreate":{"properties":{"title":{"type":"string","title":"Title"},"description":{"type":"string","title":"Description"},"category":{"type":"string","title":"Category"},"budget":{"anyOf":[{"type":"number","exclusiveMinimum":0.0},{"type":"string","pattern":"^(?!^[-+.]*$)[+-]?0*\\d*\\.?\\d*$"}],"title":"Budget"},"currency":{"type":"string","title":"Currency","default":"USD"},"deadline":{"type":"string","format":"date-time","title":"Deadline"}},"type":"object","required":["title","description","category","budget","deadline"],"title":"RFQCreate"},"RFQRead":{"properties":{"id":{"type":"integer","title":"Id"},"title":{"type":"string","title":"Title"},"description":{"type":"string","title":"Description"},"category":{"type":"string","title":"Category"},"budget":{"type":"string","pattern":"^(?!^[-+.]*$)[+-]?0*\\d*\\.?\\d*$","title":"Budget"},"currency":{"type":"string","title":"Currency"},"deadline":{"type":"string","format":"date-time","title":"Deadline"},"status":{"type":"string","title":"Status"},"created_at":{"anyOf":[{"type":"string","format":"date-time"},{"type":"null"}],"title":"Created At"}},"type":"object","required":["id","title","description","category","budget","currency","deadline","status","created_at"],"title":"RFQRead"},"RFQUpdate":{"properties":{"description":{"anyOf":[{"type":"string"},{"type":"null"}],"title":"Description"},"budget":{"anyOf":[{"type":"number"},{"type":"string","pattern":"^(?!^[-+.]*$)[+-]?0*\\d*\\.?\\d*$"},{"type":"null"}],"title":"Budget"},"deadline":{"anyOf":[{"type":"string","format":"date-time"},{"type":"null"}],"title":"Deadline"},"status":{"anyOf":[{"type":"string"},{"type":"null"}],"title":"Status"}},"type":"object","title":"RFQUpdate"},"RFQWithQuotations":{"properties":{"id":{"type":"integer","title":"Id"},"title":{"type":"string","title":"Title"},"description":{"type":"string","title":"Description"},"category":{"type":"string","title":"Category"},"budget":{"type":"string","pattern":"^(?!^[-+.]*$)[+-]?0*\\d*\\.?\\d*$","title":"Budget"},"currency":{"type":"string","title":"Currency"},"deadline":{"type":"string","format":"date-time","title":"Deadline"},"status":{"type":"string","title":"Status"},"created_at":{"anyOf":[{"type":"string","format":"date-time"},{"type":"null"}],"title":"Created At"},"quotations":{"items":{"$ref":"#/components/schemas/QuotationRead-Output"},"type":"array","title":"Quotations","default":[]}},"type":"object","required":["id","title","description","category","budget","currency","deadline","status","created_at"],"title":"RFQWithQuotations"},"SupplierCategoryRead":{"properties":{"id":{"type":"integer","title":"Id"},"name":{"type":"string","title":"Name"}},"type":"object","required":["id","name"],"title":"SupplierCategoryRead"},"SupplierDocumentRead":{"properties":{"id":{"type":"integer","title":"Id"},"document_type":{"type":"string","title":"Document Type"},"file_path":{"type":"string","title":"File Path"},"original_filename":{"anyOf":[{"type":"string"},{"type":"null"}],"title":"Original Filename"},"uploaded_at":{"type":"string","format":"date-time","title":"Uploaded At"}},"type":"object","required":["id","document_type","file_path","original_filename","uploaded_at"],"title":"SupplierDocumentRead"},"SupplierProfileRead":{"properties":{"id":{"type":"integer","title":"Id"},"company_name":{"type":"string","title":"Company Name"},"contact_email":{"type":"string","title":"Contact Email"},"contact_phone":{"anyOf":[{"type":"string"},{"type":"null"}],"title":"Contact Phone"},"address":{"anyOf":[{"type":"string"},{"type":"null"}],"title":"Address"},"preferred_currency":{"anyOf":[{"type":"string"},{"type":"null"}],"title":"Preferred Currency"},"invitations_sent":{"type":"integer","title":"Invitations Sent"},"last_invited_at":{"anyOf":[{"type":"string","format":"date-time"},{"type":"null"}],"title":"Last Invited At"},"documents":{"items":{"$ref":"#/components/schemas/SupplierDocumentRead"},"type":"array","title":"Documents","default":[]},"categories":{"items":{"$ref":"#/components/schemas/SupplierCategoryRead"},"type":"array","title":"Categories","default":[]}},"type":"object","required":["id","company_name","contact_email","contact_phone","address","preferred_currency","invitations_sent","last_invited_at"],"title":"SupplierProfileRead"},"SupplierRegistrationResponse":{"properties":{"user_id":{"type":"integer","title":"User Id"},"supplier_id":{"type":"integer","title":"Supplier Id"}},"type":"object","required":["user_id","supplier_id"],"title":"SupplierRegistrationResponse"},"Token":{"properties":{"access_token":{"type":"string","title":"Access Token"},"token_type":{"type":"string","title":"Token Type","default":"bearer"}},"type":"object","required":["access_token"],"title":"Token"},"UserCreate":{"properties":{"email":{"type":"string","title":"Email"},"full_name":{"type":"string","title":"Full Name"},"password":{"type":"string","minLength":8,"title":"Password"},"role":{"type":"string","title":"Role"}},"type":"object","required":["email","full_name","password","role"],"title":"UserCreate"},"UserRead":{"properties":{"email":{"type":"string","title":"Email"},"full_name":{"type":"string","title":"Full Name"},"id":{"type":"integer","title":"Id"},"role":{"type":"string","title":"Role"},"is_active":{"type":"boolean","title":"Is Active"},"created_at":{"anyOf":[{"type":"string","format":"date-time"},{"type":"null"}],"title":"Created At"}},"type":"object","required":["email","full_name","id","role","is_active","created_at"],"title":"UserRead"},"ValidationError":{"properties":{"loc":{"items":{"anyOf":[{"type":"string"},{"type":"integer"}]},"type":"array","title":"Location"},"msg":{"type":"string","title":"Message"},"type":{"type":"string","title":"Error Type"}},"type":"object","required":["loc","msg","type"],"title":"ValidationError"}},"securitySchemes":{"OAuth2PasswordBearer":{"type":"oauth2","flows":{"password":{"scopes":{},"tokenUrl":"/api/auth/token"}}}}}}
